zi_mcp/__init__.py
zi_mcp/client.py
zi_mcp/server.py
zi_mcp-0.1.3.dist-info/METADATA
zi_mcp-0.1.3.dist-info/WHEEL
zi_mcp-0.1.3.dist-info/entry_points.txt
zi_mcp-0.1.3.dist-info/RECORD
