Metadata-Version: 2.4
Name: zi-mcp
Version: 0.1.3
Summary: MCP server for Zi - Your AI companion for life guidance
Project-URL: Homepage, https://ziai.chat
Project-URL: Repository, https://github.com/bigsmall-jsc/zi
Author-email: Zi Team <hello@ziai.chat>
License-Expression: MIT
Keywords: ai,astrology,bazi,companion,mcp,zi
Classifier: Development Status :: 3 - Alpha
Classifier: Intended Audience :: Developers
Classifier: License :: OSI Approved :: MIT License
Classifier: Programming Language :: Python :: 3
Classifier: Programming Language :: Python :: 3.10
Classifier: Programming Language :: Python :: 3.11
Classifier: Programming Language :: Python :: 3.12
Requires-Python: >=3.10
Requires-Dist: httpx>=0.25.0
Requires-Dist: mcp>=1.0.0
